{
  "__inputs": [
    {
      "name": "DS_PROMETHEUS",
      "label": "prometheus",
      "description": "",
      "type": "datasource",
      "pluginId": "prometheus",
      "pluginName": "Prometheus"
    }
  ],
  "__requires": [
    {
      "type": "grafana",
      "id": "grafana",
      "name": "Grafana",
      "version": "5.3.2"
    },
    {
      "type": "panel",
      "id": "graph",
      "name": "Graph",
      "version": "5.0.0"
    },
    {
      "type": "datasource",
      "id": "prometheus",
      "name": "Prometheus",
      "version": "5.0.0"
    },
    {
      "type": "panel",
      "id": "singlestat",
      "name": "Singlestat",
      "version": "5.0.0"
    }
  ],
  "annotations": {
    "list": [
      {
        "builtIn": 1,
        "datasource": "-- Grafana --",
        "enable": true,
        "hide": true,
        "iconColor": "rgba(0, 211, 255, 1)",
        "name": "Annotations & Alerts",
        "type": "dashboard"
      }
    ]
  },
  "description": "Elasticsearch detailed dashboard",
  "editable": true,
  "gnetId": 4358,
  "graphTooltip": 1,
  "id": null,
  "iteration": 1541533687562,
  "links": [],
  "panels": [
    {
      "collapsed": false,
      "gridPos": {
        "h": 1,
        "w": 24,
        "x": 0,
        "y": 0
      },
      "id": 57,
      "panels": [],
      "repeat": null,
      "title": "Cluster",
      "type": "row"
    },
    {
      "cacheTimeout": null,
      "colorBackground": true,
      "colorValue": false,
      "colors": [
        "rgba(50, 172, 45, 0.97)",
        "#967302",
        "rgba(245, 54, 54, 0.9)"
      ],
      "datasource": "${DS_PROMETHEUS}",
      "editable": true,
      "error": false,
      "format": "none",
      "gauge": {
        "maxValue": 100,
        "minValue": 0,
        "show": false,
        "thresholdLabels": false,
        "thresholdMarkers": true
      },
      "gridPos": {
        "h": 4,
        "w": 6,
        "x": 0,
        "y": 1
      },
      "height": "150",
      "id": 8,
      "interval": null,
      "links": [],
      "mappingType": 1,
      "mappingTypes": [
        {
          "name": "value to text",
          "value": 1
        },
        {
          "name": "range to text",
          "value": 2
        }
      ],
      "maxDataPoints": 100,
      "nullPointMode": "connected",
      "nullText": null,
      "postfix": "",
      "postfixFontSize": "50%",
      "prefix": "",
      "prefixFontSize": "50%",
      "rangeMaps": [
        {
          "from": "null",
          "text": "N/A",
          "to": "null"
        }
      ],
      "sparkline": {
        "fillColor": "rgba(31, 118, 189, 0.18)",
        "full": true,
        "lineColor": "rgb(31, 120, 193)",
        "show": true
      },
      "tableColumn": "",
      "targets": [
        {
          "expr": "max(elasticsearch_cluster_health_status{color=\"green\",cluster=~\"$cluster\"})*0 + max(elasticsearch_cluster_health_status{color=\"yellow\",cluster=~\"$cluster\"})*1 + max(elasticsearch_cluster_health_status{color=\"red\",cluster=~\"$cluster\"})*2",
          "format": "time_series",
          "intervalFactor": 2,
          "legendFormat": "",
          "metric": "",
          "refId": "A",
          "step": 40
        }
      ],
      "thresholds": "1,2",
      "title": "Cluster health status",
      "transparent": false,
      "type": "singlestat",
      "valueFontSize": "80%",
      "valueMaps": [
        {
          "op": "=",
          "text": "GREEN",
          "value": "0"
        },
        {
          "op": "=",
          "text": "YELLOW",
          "value": "1"
        },
        {
          "op": "=",
          "text": "RED",
          "value": "2"
        }
      ],
      "valueName": "current"
    },
    {
      "cacheTimeout": null,
      "colorBackground": false,
      "colorValue": false,
      "colors": [
        "rgba(245, 54, 54, 0.9)",
        "rgba(237, 129, 40, 0.89)",
        "rgba(50, 172, 45, 0.97)"
      ],
      "datasource": "${DS_PROMETHEUS}",
      "editable": true,
      "error": false,
      "format": "none",
      "gauge": {
        "maxValue": 100,
        "minValue": 0,
        "show": false,
        "thresholdLabels": false,
        "thresholdMarkers": true
      },
      "gridPos": {
        "h": 4,
        "w": 2,
        "x": 6,
        "y": 1
      },
      "height": "150",
      "id": 10,
      "interval": null,
      "links": [],
      "mappingType": 1,
      "mappingTypes": [
        {
          "name": "value to text",
          "value": 1
        },
        {
          "name": "range to text",
          "value": 2
        }
      ],
      "maxDataPoints": 100,
      "nullPointMode": "connected",
      "nullText": null,
      "postfix": "",
      "postfixFontSize": "50%",
      "prefix": "",
      "prefixFontSize": "50%",
      "rangeMaps": [
        {
          "from": "null",
          "text": "N/A",
          "to": "null"
        }
      ],
      "sparkline": {
        "fillColor": "rgba(31, 118, 189, 0.18)",
        "full": false,
        "lineColor": "rgb(31, 120, 193)",
        "show": false
      },
      "tableColumn": "",
      "targets": [
        {
          "expr": "max(elasticsearch_cluster_health_number_of_nodes)",
          "format": "time_series",
          "interval": "",
          "intervalFactor": 2,
          "legendFormat": "",
          "metric": "",
          "refId": "A",
          "step": 40
        }
      ],
      "thresholds": "",
      "title": "Nodes",
      "transparent": false,
      "type": "singlestat",
      "valueFontSize": "80%",
      "valueMaps": [
        {
          "op": "=",
          "text": "N/A",
          "value": "null"
        }
      ],
      "valueName": "current"
    },
    {
      "cacheTimeout": null,
      "colorBackground": false,
      "colorValue": false,
      "colors": [
        "rgba(245, 54, 54, 0.9)",
        "rgba(237, 129, 40, 0.89)",
        "rgba(50, 172, 45, 0.97)"
      ],
      "datasource": "${DS_PROMETHEUS}",
      "editable": true,
      "error": false,
      "format": "none",
      "gauge": {
        "maxValue": 100,
        "minValue": 0,
        "show": false,
        "thresholdLabels": false,
        "thresholdMarkers": true
      },
      "gridPos": {
        "h": 4,
        "w": 2,
        "x": 8,
        "y": 1
      },
      "height": "150",
      "id": 9,
      "interval": null,
      "links": [],
      "mappingType": 1,
      "mappingTypes": [
        {
          "name": "value to text",
          "value": 1
        },
        {
          "name": "range to text",
          "value": 2
        }
      ],
      "maxDataPoints": 100,
      "nullPointMode": "connected",
      "nullText": null,
      "postfix": "",
      "postfixFontSize": "50%",
      "prefix": "",
      "prefixFontSize": "50%",
      "rangeMaps": [
        {
          "from": "null",
          "text": "N/A",
          "to": "null"
        }
      ],
      "sparkline": {
        "fillColor": "rgba(31, 118, 189, 0.18)",
        "full": false,
        "lineColor": "rgb(31, 120, 193)",
        "show": false
      },
      "tableColumn": "",
      "targets": [
        {
          "expr": "max(elasticsearch_cluster_health_number_of_data_nodes{cluster=\"$cluster\"})",
          "format": "time_series",
          "interval": "",
          "intervalFactor": 2,
          "legendFormat": "",
          "metric": "",
          "refId": "A",
          "step": 40
        }
      ],
      "thresholds": "",
      "title": "Data nodes",
      "transparent": false,
      "type": "singlestat",
      "valueFontSize": "80%",
      "valueMaps": [
        {
          "op": "=",
          "text": "N/A",
          "value": "null"
        }
      ],
      "valueName": "current"
    },
    {
      "cacheTimeout": null,
      "colorBackground": true,
      "colorValue": false,
      "colors": [
        "rgba(50, 172, 45, 0.97)",
        "rgba(237, 129, 40, 0.89)",
        "rgba(245, 54, 54, 0.9)"
      ],
      "datasource": "${DS_PROMETHEUS}",
      "editable": true,
      "error": false,
      "format": "none",
      "gauge": {
        "maxValue": 100,
        "minValue": 0,
        "show": false,
        "thresholdLabels": false,
        "thresholdMarkers": true
      },
      "gridPos": {
        "h": 4,
        "w": 2,
        "x": 10,
        "y": 1
      },
      "height": "150",
      "hideTimeOverride": true,
      "id": 16,
      "interval": null,
      "links": [],
      "mappingType": 1,
      "mappingTypes": [
        {
          "name": "value to text",
          "value": 1
        },
        {
          "name": "range to text",
          "value": 2
        }
      ],
      "maxDataPoints": 100,
      "nullPointMode": "connected",
      "nullText": null,
      "postfix": "",
      "postfixFontSize": "50%",
      "prefix": "",
      "prefixFontSize": "50%",
      "rangeMaps": [
        {
          "from": "null",
          "text": "N/A",
          "to": "null"
        }
      ],
      "sparkline": {
        "fillColor": "rgba(31, 118, 189, 0.18)",
        "full": false,
        "lineColor": "rgb(31, 120, 193)",
        "show": true
      },
      "tableColumn": "",
      "targets": [
        {
          "expr": "max(elasticsearch_cluster_health_number_of_pending_tasks{cluster=\"$cluster\"})",
          "format": "time_series",
          "interval": "",
          "intervalFactor": 2,
          "legendFormat": "",
          "metric": "",
          "refId": "A",
          "step": 40
        }
      ],
      "thresholds": "50.80",
      "title": "Pending tasks",
      "transparent": false,
      "type": "singlestat",
      "valueFontSize": "80%",
      "valueMaps": [
        {
          "op": "=",
          "text": "N/A",
          "value": "null"
        }
      ],
      "valueName": "current"
    },
    {
      "cacheTimeout": null,
      "colorBackground": false,
      "colorValue": false,
      "colors": [
        "rgba(245, 54, 54, 0.9)",
        "rgba(237, 129, 40, 0.89)",
        "rgba(50, 172, 45, 0.97)"
      ],
      "datasource": "${DS_PROMETHEUS}",
      "editable": true,
      "error": false,
      "format": "none",
      "gauge": {
        "maxValue": 100,
        "minValue": 0,
        "show": false,
        "thresholdLabels": false,
        "thresholdMarkers": true
      },
      "gridPos": {
        "h": 4,
        "w": 2,
        "x": 12,
        "y": 1
      },
      "height": "150",
      "hideTimeOverride": true,
      "id": 50,
      "interval": null,
      "links": [],
      "mappingType": 1,
      "mappingTypes": [
        {
          "name": "value to text",
          "value": 1
        },
        {
          "name": "range to text",
          "value": 2
        }
      ],
      "maxDataPoints": 100,
      "nullPointMode": "connected",
      "nullText": null,
      "postfix": "",
      "postfixFontSize": "50%",
      "prefix": "",
      "prefixFontSize": "50%",
      "rangeMaps": [
        {
          "from": "null",
          "text": "N/A",
          "to": "null"
        }
      ],
      "sparkline": {
        "fillColor": "rgba(31, 118, 189, 0.18)",
        "full": false,
        "lineColor": "rgb(31, 120, 193)",
        "show": false
      },
      "tableColumn": "",
      "targets": [
        {
          "expr": "elasticsearch_process_cpu_percent",
          "format": "time_series",
          "instant": true,
          "interval": "",
          "intervalFactor": 2,
          "legendFormat": "",
          "metric": "",
          "refId": "A",
          "step": 40
        }
      ],
      "thresholds": "",
      "title": "Cluster CPU Number",
      "transparent": false,
      "type": "singlestat",
      "valueFontSize": "80%",
      "valueMaps": [
        {
          "op": "=",
          "text": "N/A",
          "value": "null"
        }
      ],
      "valueName": "current"
    },
    {
      "cacheTimeout": null,
      "colorBackground": false,
      "colorValue": false,
      "colors": [
        "rgba(245, 54, 54, 0.9)",
        "rgba(237, 129, 40, 0.89)",
        "rgba(50, 172, 45, 0.97)"
      ],
      "datasource": "${DS_PROMETHEUS}",
      "editable": true,
      "error": false,
      "format": "decbytes",
      "gauge": {
        "maxValue": 100,
        "minValue": 0,
        "show": false,
        "thresholdLabels": false,
        "thresholdMarkers": true
      },
      "gridPos": {
        "h": 4,
        "w": 2,
        "x": 14,
        "y": 1
      },
      "height": "150",
      "hideTimeOverride": true,
      "id": 51,
      "interval": null,
      "links": [],
      "mappingType": 1,
      "mappingTypes": [
        {
          "name": "value to text",
          "value": 1
        },
        {
          "name": "range to text",
          "value": 2
        }
      ],
      "maxDataPoints": 100,
      "nullPointMode": "connected",
      "nullText": null,
      "postfix": "",
      "postfixFontSize": "50%",
      "prefix": "",
      "prefixFontSize": "50%",
      "rangeMaps": [
        {
          "from": "null",
          "text": "N/A",
          "to": "null"
        }
      ],
      "sparkline": {
        "fillColor": "rgba(31, 118, 189, 0.18)",
        "full": false,
        "lineColor": "rgb(31, 120, 193)",
        "show": true
      },
      "tableColumn": "",
      "targets": [
        {
          "expr": "sum(node_memory_MemTotal_bytes{instance=~\"$node\",job=\"node\"})",
          "format": "time_series",
          "interval": "",
          "intervalFactor": 2,
          "legendFormat": "",
          "metric": "",
          "refId": "A",
          "step": 40
        }
      ],
      "thresholds": "",
      "title": "Total Cluster Ram",
      "transparent": false,
      "type": "singlestat",
      "valueFontSize": "80%",
      "valueMaps": [
        {
          "op": "=",
          "text": "N/A",
          "value": "null"
        }
      ],
      "valueName": "current"
    },
    {
      "cacheTimeout": null,
      "colorBackground": false,
      "colorValue": false,
      "colors": [
        "rgba(245, 54, 54, 0.9)",
        "rgba(237, 129, 40, 0.89)",
        "rgba(50, 172, 45, 0.97)"
      ],
      "datasource": "${DS_PROMETHEUS}",
      "editable": true,
      "error": false,
      "format": "decbytes",
      "gauge": {
        "maxValue": 100,
        "minValue": 0,
        "show": false,
        "thresholdLabels": false,
        "thresholdMarkers": true
      },
      "gridPos": {
        "h": 4,
        "w": 2,
        "x": 16,
        "y": 1
      },
      "height": "150",
      "hideTimeOverride": true,
      "id": 52,
      "interval": null,
      "links": [],
      "mappingType": 1,
      "mappingTypes": [
        {
          "name": "value to text",
          "value": 1
        },
        {
          "name": "range to text",
          "value": 2
        }
      ],
      "maxDataPoints": 100,
      "nullPointMode": "connected",
      "nullText": null,
      "postfix": "",
      "postfixFontSize": "50%",
      "prefix": "",
      "prefixFontSize": "50%",
      "rangeMaps": [
        {
          "from": "null",
          "text": "N/A",
          "to": "null"
        }
      ],
      "sparkline": {
        "fillColor": "rgba(31, 118, 189, 0.18)",
        "full": false,
        "lineColor": "rgb(31, 120, 193)",
        "show": true
      },
      "tableColumn": "",
      "targets": [
        {
          "expr": "sum(elasticsearch_filesystem_data_size_bytes) by (cluster)",
          "format": "time_series",
          "interval": "",
          "intervalFactor": 2,
          "legendFormat": "",
          "metric": "",
          "refId": "A",
          "step": 40
        }
      ],
      "thresholds": "",
      "title": "Total ElasticSearch disk Size",
      "transparent": false,
      "type": "singlestat",
      "valueFontSize": "80%",
      "valueMaps": [
        {
          "op": "=",
          "text": "N/A",
          "value": "null"
        }
      ],
      "valueName": "current"
    },
    {
      "cacheTimeout": null,
      "colorBackground": true,
      "colorValue": false,
      "colors": [
        "rgba(245, 54, 54, 0.9)",
        "rgba(237, 129, 40, 0.89)",
        "rgba(50, 172, 45, 0.97)"
      ],
      "datasource": "${DS_PROMETHEUS}",
      "editable": true,
      "error": false,
      "format": "percent",
      "gauge": {
        "maxValue": 100,
        "minValue": 0,
        "show": false,
        "thresholdLabels": true,
        "thresholdMarkers": true
      },
      "gridPos": {
        "h": 4,
        "w": 2,
        "x": 18,
        "y": 1
      },
      "height": "150",
      "hideTimeOverride": true,
      "id": 68,
      "interval": null,
      "links": [],
      "mappingType": 1,
      "mappingTypes": [
        {
          "name": "value to text",
          "value": 1
        },
        {
          "name": "range to text",
          "value": 2
        }
      ],
      "maxDataPoints": 100,
      "nullPointMode": "connected",
      "nullText": null,
      "postfix": "",
      "postfixFontSize": "50%",
      "prefix": "",
      "prefixFontSize": "50%",
      "rangeMaps": [
        {
          "from": "null",
          "text": "N/A",
          "to": "null"
        }
      ],
      "sparkline": {
        "fillColor": "rgba(31, 118, 189, 0.18)",
        "full": false,
        "lineColor": "rgb(31, 120, 193)",
        "show": false
      },
      "tableColumn": "",
      "targets": [
        {
          "expr": "elasticsearch_filesystem_data_free_bytes / elasticsearch_filesystem_data_size_bytes * 100",
          "format": "time_series",
          "interval": "",
          "intervalFactor": 2,
          "legendFormat": "",
          "metric": "",
          "refId": "A",
          "step": 40
        }
      ],
      "thresholds": "5,10",
      "title": "Cluster Disk",
      "transparent": false,
      "type": "singlestat",
      "valueFontSize": "80%",
      "valueMaps": [
        {
          "op": "=",
          "text": "N/A",
          "value": "null"
        }
      ],
      "valueName": "current"
    },
    {
      "cacheTimeout": null,
      "colorBackground": true,
      "colorValue": false,
      "colors": [
        "rgba(50, 172, 45, 0.97)",
        "rgba(237, 129, 40, 0.89)",
        "rgba(245, 54, 54, 0.9)"
      ],
      "datasource": "${DS_PROMETHEUS}",
      "decimals": null,
      "editable": true,
      "error": false,
      "format": "none",
      "gauge": {
        "maxValue": 100,
        "minValue": 0,
        "show": false,
        "thresholdLabels": false,
        "thresholdMarkers": true
      },
      "gridPos": {
        "h": 4,
        "w": 4,
        "x": 20,
        "y": 1
      },
      "height": "150",
      "hideTimeOverride": true,
      "id": 56,
      "interval": null,
      "links": [],
      "mappingType": 1,
      "mappingTypes": [
        {
          "name": "value to text",
          "value": 1
        },
        {
          "name": "range to text",
          "value": 2
        }
      ],
      "maxDataPoints": 100,
      "nullPointMode": "connected",
      "nullText": null,
      "postfix": "",
      "postfixFontSize": "50%",
      "prefix": "",
      "prefixFontSize": "50%",
      "rangeMaps": [
        {
          "from": "null",
          "text": "N/A",
          "to": "null"
        }
      ],
      "sparkline": {
        "fillColor": "rgba(31, 118, 189, 0.18)",
        "full": false,
        "lineColor": "rgb(31, 120, 193)",
        "show": true
      },
      "tableColumn": "",
      "targets": [
        {
          "expr": "sum(elasticsearch_os_load1)",
          "format": "time_series",
          "instant": false,
          "interval": "",
          "intervalFactor": 2,
          "legendFormat": "",
          "metric": "",
          "refId": "A",
          "step": 40
        }
      ],
      "thresholds": "12,30",
      "title": "Total Cluster Load",
      "transparent": false,
      "type": "singlestat",
      "valueFontSize": "80%",
      "valueMaps": [
        {
          "op": "=",
          "text": "N/A",
          "value": "null"
        }
      ],
      "valueName": "current"
    },
    {
      "collapsed": false,
      "gridPos": {
        "h": 1,
        "w": 24,
        "x": 0,
        "y": 5
      },
      "id": 58,
      "panels": [],
      "repeat": null,
      "title": "Shards",
      "type": "row"
    },
    {
      "cacheTimeout": null,
      "colorBackground": false,
      "colorValue": false,
      "colors": [
        "rgba(245, 54, 54, 0.9)",
        "rgba(237, 129, 40, 0.89)",
        "rgba(50, 172, 45, 0.97)"
      ],
      "datasource": "${DS_PROMETHEUS}",
      "editable": true,
      "error": false,
      "format": "none",
      "gauge": {
        "maxValue": 100,
        "minValue": 0,
        "show": false,
        "thresholdLabels": false,
        "thresholdMarkers": true
      },
      "gridPos": {
        "h": 3,
        "w": 4,
        "x": 0,
        "y": 6
      },
      "height": "50",
      "id": 11,
      "interval": null,
      "links": [],
      "mappingType": 1,
      "mappingTypes": [
        {
          "name": "value to text",
          "value": 1
        },
        {
          "name": "range to text",
          "value": 2
        }
      ],
      "maxDataPoints": 100,
      "minSpan": 4,
      "nullPointMode": "connected",
      "nullText": null,
      "postfix": "",
      "postfixFontSize": "50%",
      "prefix": "",
      "prefixFontSize": "50%",
      "rangeMaps": [
        {
          "from": "null",
          "text": "N/A",
          "to": "null"
        }
      ],
      "repeat": "shard_type",
      "sparkline": {
        "fillColor": "rgba(31, 118, 189, 0.18)",
        "full": true,
        "lineColor": "rgb(31, 120, 193)",
        "show": true
      },
      "tableColumn": "",
      "targets": [
        {
          "expr": "max(elasticsearch_cluster_health_active_primary_shards)",
          "format": "time_series",
          "instant": true,
          "intervalFactor": 2,
          "legendFormat": "",
          "refId": "A",
          "step": 40
        }
      ],
      "thresholds": "",
      "title": "active primary shards",
      "type": "singlestat",
      "valueFontSize": "80%",
      "valueMaps": [
        {
          "op": "=",
          "text": "N/A",
          "value": "null"
        }
      ],
      "valueName": "current"
    },
    {
      "cacheTimeout": null,
      "colorBackground": false,
      "colorValue": false,
      "colors": [
        "rgba(245, 54, 54, 0.9)",
        "rgba(237, 129, 40, 0.89)",
        "rgba(50, 172, 45, 0.97)"
      ],
      "datasource": "${DS_PROMETHEUS}",
      "editable": true,
      "error": false,
      "format": "none",
      "gauge": {
        "maxValue": 100,
        "minValue": 0,
        "show": false,
        "thresholdLabels": false,
        "thresholdMarkers": true
      },
      "gridPos": {
        "h": 3,
        "w": 4,
        "x": 4,
        "y": 6
      },
      "height": "50",
      "id": 39,
      "interval": null,
      "links": [],
      "mappingType": 1,
      "mappingTypes": [
        {
          "name": "value to text",
          "value": 1
        },
        {
          "name": "range to text",
          "value": 2
        }
      ],
      "maxDataPoints": 100,
      "minSpan": 4,
      "nullPointMode": "connected",
      "nullText": null,
      "postfix": "",
      "postfixFontSize": "50%",
      "prefix": "",
      "prefixFontSize": "50%",
      "rangeMaps": [
        {
          "from": "null",
          "text": "N/A",
          "to": "null"
        }
      ],
      "sparkline": {
        "fillColor": "rgba(31, 118, 189, 0.18)",
        "full": true,
        "lineColor": "rgb(31, 120, 193)",
        "show": true
      },
      "tableColumn": "",
      "targets": [
        {
          "expr": "max(elasticsearch_cluster_health_active_shards{cluster=\"$cluster\"})",
          "format": "time_series",
          "instant": true,
          "intervalFactor": 2,
          "legendFormat": "",
          "refId": "A",
          "step": 40
        }
      ],
      "thresholds": "",
      "title": "active shards",
      "type": "singlestat",
      "valueFontSize": "80%",
      "valueMaps": [
        {
          "op": "=",
          "text": "N/A",
          "value": "null"
        }
      ],
      "valueName": "current"
    },
    {
      "cacheTimeout": null,
      "colorBackground": true,
      "colorValue": false,
      "colors": [
        "rgba(50, 172, 45, 0.97)",
        "rgba(237, 129, 40, 0.89)",
        "rgba(245, 54, 54, 0.9)"
      ],
      "datasource": "${DS_PROMETHEUS}",
      "editable": true,
      "error": false,
      "format": "none",
      "gauge": {
        "maxValue": 100,
        "minValue": 0,
        "show": false,
        "thresholdLabels": false,
        "thresholdMarkers": true
      },
      "gridPos": {
        "h": 3,
        "w": 4,
        "x": 8,
        "y": 6
      },
      "height": "50",
      "id": 40,
      "interval": null,
      "links": [],
      "mappingType": 1,
      "mappingTypes": [
        {
          "name": "value to text",
          "value": 1
        },
        {
          "name": "range to text",
          "value": 2
        }
      ],
      "maxDataPoints": 100,
      "minSpan": 4,
      "nullPointMode": "connected",
      "nullText": null,
      "postfix": "",
      "postfixFontSize": "50%",
      "prefix": "",
      "prefixFontSize": "50%",
      "rangeMaps": [
        {
          "from": "null",
          "text": "N/A",
          "to": "null"
        }
      ],
      "sparkline": {
        "fillColor": "rgba(31, 118, 189, 0.18)",
        "full": true,
        "lineColor": "rgb(31, 120, 193)",
        "show": true
      },
      "tableColumn": "",
      "targets": [
        {
          "expr": "max(elasticsearch_cluster_health_initializing_shards{cluster=\"$cluster\"})",
          "format": "time_series",
          "instant": true,
          "intervalFactor": 2,
          "legendFormat": "",
          "refId": "A",
          "step": 40
        }
      ],
      "thresholds": "10,20",
      "title": "initializing shards",
      "type": "singlestat",
      "valueFontSize": "80%",
      "valueMaps": [
        {
          "op": "=",
          "text": "N/A",
          "value": "null"
        }
      ],
      "valueName": "current"
    },
    {
      "cacheTimeout": null,
      "colorBackground": true,
      "colorValue": false,
      "colors": [
        "rgba(50, 172, 45, 0.97)",
        "rgba(237, 129, 40, 0.89)",
        "rgba(245, 54, 54, 0.9)"
      ],
      "datasource": "${DS_PROMETHEUS}",
      "editable": true,
      "error": false,
      "format": "none",
      "gauge": {
        "maxValue": 100,
        "minValue": 0,
        "show": false,
        "thresholdLabels": false,
        "thresholdMarkers": true
      },
      "gridPos": {
        "h": 3,
        "w": 4,
        "x": 12,
        "y": 6
      },
      "height": "50",
      "id": 41,
      "interval": null,
      "links": [],
      "mappingType": 1,
      "mappingTypes": [
        {
          "name": "value to text",
          "value": 1
        },
        {
          "name": "range to text",
          "value": 2
        }
      ],
      "maxDataPoints": 100,
      "minSpan": 4,
      "nullPointMode": "connected",
      "nullText": null,
      "postfix": "",
      "postfixFontSize": "50%",
      "prefix": "",
      "prefixFontSize": "50%",
      "rangeMaps": [
        {
          "from": "null",
          "text": "N/A",
          "to": "null"
        }
      ],
      "sparkline": {
        "fillColor": "rgba(31, 118, 189, 0.18)",
        "full": true,
        "lineColor": "rgb(31, 120, 193)",
        "show": true
      },
      "tableColumn": "",
      "targets": [
        {
          "expr": "max(elasticsearch_cluster_health_relocating_shards{cluster=\"$cluster\"})",
          "format": "time_series",
          "instant": false,
          "intervalFactor": 2,
          "legendFormat": "",
          "refId": "A",
          "step": 40
        }
      ],
      "thresholds": "10,20",
      "title": "relocating shards",
      "type": "singlestat",
      "valueFontSize": "80%",
      "valueMaps": [
        {
          "op": "=",
          "text": "N/A",
          "value": "null"
        }
      ],
      "valueName": "current"
    },
    {
      "cacheTimeout": null,
      "colorBackground": true,
      "colorValue": false,
      "colors": [
        "rgba(50, 172, 45, 0.97)",
        "rgba(237, 129, 40, 0.89)",
        "rgba(245, 54, 54, 0.9)"
      ],
      "datasource": "${DS_PROMETHEUS}",
      "editable": true,
      "error": false,
      "format": "none",
      "gauge": {
        "maxValue": 100,
        "minValue": 0,
        "show": false,
        "thresholdLabels": false,
        "thresholdMarkers": true
      },
      "gridPos": {
        "h": 3,
        "w": 4,
        "x": 16,
        "y": 6
      },
      "height": "50",
      "id": 42,
      "interval": null,
      "links": [],
      "mappingType": 1,
      "mappingTypes": [
        {
          "name": "value to text",
          "value": 1
        },
        {
          "name": "range to text",
          "value": 2
        }
      ],
      "maxDataPoints": 100,
      "minSpan": 4,
      "nullPointMode": "connected",
      "nullText": null,
      "postfix": "",
      "postfixFontSize": "50%",
      "prefix": "",
      "prefixFontSize": "50%",
      "rangeMaps": [
        {
          "from": "null",
          "text": "N/A",
          "to": "null"
        }
      ],
      "sparkline": {
        "fillColor": "rgba(31, 118, 189, 0.18)",
        "full": true,
        "lineColor": "rgb(31, 120, 193)",
        "show": true
      },
      "tableColumn": "",
      "targets": [
        {
          "expr": "max(elasticsearch_cluster_health_delayed_unassigned_shards{cluster=\"$cluster\"})",
          "format": "time_series",
          "instant": true,
          "intervalFactor": 2,
          "legendFormat": "",
          "refId": "A",
          "step": 40
        }
      ],
      "thresholds": "10,15",
      "title": "unassigned shards",
      "type": "singlestat",
      "valueFontSize": "80%",
      "valueMaps": [
        {
          "op": "=",
          "text": "N/A",
          "value": "null"
        }
      ],
      "valueName": "current"
    },
    {
      "collapsed": false,
      "gridPos": {
        "h": 1,
        "w": 24,
        "x": 0,
        "y": 9
      },
      "id": 59,
      "panels": [],
      "repeat": null,
      "title": "Disk",
      "type": "row"
    },
    {
      "cacheTimeout": null,
      "colorBackground": true,
      "colorValue": false,
      "colors": [
        "#d44a3a",
        "rgba(237, 129, 40, 0.89)",
        "#299c46"
      ],
      "datasource": "${DS_PROMETHEUS}",
      "format": "percent",
      "gauge": {
        "maxValue": 100,
        "minValue": 0,
        "show": false,
        "thresholdLabels": false,
        "thresholdMarkers": true
      },
      "gridPos": {
        "h": 4,
        "w": 24,
        "x": 0,
        "y": 10
      },
      "id": 53,
      "interval": null,
      "links": [],
      "mappingType": 1,
      "mappingTypes": [
        {
          "name": "value to text",
          "value": 1
        },
        {
          "name": "range to text",
          "value": 2
        }
      ],
      "maxDataPoints": 100,
      "minSpan": 4,
      "nullPointMode": "connected",
      "nullText": null,
      "postfix": "",
      "postfixFontSize": "50%",
      "prefix": "",
      "prefixFontSize": "50%",
      "rangeMaps": [
        {
          "from": "null",
          "text": "N/A",
          "to": "null"
        }
      ],
      "repeat": "node",
      "repeatDirection": "h",
      "sparkline": {
        "fillColor": "rgba(31, 118, 189, 0.18)",
        "full": false,
        "lineColor": "rgb(31, 120, 193)",
        "show": false
      },
      "tableColumn": "",
      "targets": [
        {
          "expr": "elasticsearch_filesystem_data_free_bytes{instance=\"$node\"} / elasticsearch_filesystem_data_size_bytes{instance=\"$node\"} * 100",
          "format": "time_series",
          "intervalFactor": 2,
          "refId": "A"
        }
      ],
      "thresholds": "15,30",
      "title": "Disk Free % $node",
      "type": "singlestat",
      "valueFontSize": "80%",
      "valueMaps": [
        {
          "op": "=",
          "text": "N/A",
          "value": "null"
        }
      ],
      "valueName": "avg"
    },
    {
      "collapsed": false,
      "gridPos": {
        "h": 1,
        "w": 24,
        "x": 0,
        "y": 14
      },
      "id": 60,
      "panels": [],
      "repeat": null,
      "title": "System",
      "type": "row"
    },
    {
      "aliasColors": {},
      "bars": false,
      "dashLength": 10,
      "dashes": false,
      "datasource": "${DS_PROMETHEUS}",
      "editable": true,
      "error": false,
      "fill": 1,
      "grid": {},
      "gridPos": {
        "h": 10,
        "w": 12,
        "x": 0,
        "y": 15
      },
      "height": "400",
      "id": 30,
      "legend": {
        "alignAsTable": true,
        "avg": true,
        "current": true,
        "hideEmpty": false,
        "hideZero": false,
        "max": true,
        "min": true,
        "rightSide": false,
        "show": true,
        "sortDesc": true,
        "total": false,
        "values": true
      },
      "lines": true,
      "linewidth": 1,
      "links": [],
      "nullPointMode": "connected",
      "percentage": false,
      "pointradius": 5,
      "points": false,
      "renderer": "flot",
      "seriesOverrides": [],
      "spaceLength": 10,
      "stack": false,
      "steppedLine": false,
      "targets": [
        {
          "expr": "avg(elasticsearch_process_cpu_percent) by (instance)",
          "format": "time_series",
          "instant": false,
          "interval": "",
          "intervalFactor": 2,
          "legendFormat": "{{ instance }}",
          "metric": "",
          "refId": "A",
          "step": 10
        }
      ],
      "thresholds": [],
      "timeFrom": null,
      "timeShift": null,
      "title": "CPU usage",
      "tooltip": {
        "msResolution": false,
        "shared": true,
        "sort": 0,
        "value_type": "cumulative"
      },
      "transparent": false,
      "type": "graph",
      "xaxis": {
        "buckets": null,
        "mode": "time",
        "name": null,
        "show": true,
        "values": []
      },
      "yaxes": [
        {
          "format": "percent",
          "label": "CPU usage",
          "logBase": 1,
          "max": 100,
          "min": 0,
          "show": true
        },
        {
          "format": "short",
          "label": null,
          "logBase": 1,
          "max": null,
          "min": null,
          "show": false
        }
      ],
      "yaxis": {
        "align": false,
        "alignLevel": null
      }
    },
    {
      "aliasColors": {},
      "bars": false,
      "dashLength": 10,
      "dashes": false,
      "datasource": "${DS_PROMETHEUS}",
      "editable": true,
      "error": false,
      "fill": 1,
      "grid": {},
      "gridPos": {
        "h": 10,
        "w": 12,
        "x": 12,
        "y": 15
      },
      "height": "400",
      "id": 47,
      "legend": {
        "alignAsTable": true,
        "avg": true,
        "current": true,
        "hideEmpty": false,
        "hideZero": false,
        "max": true,
        "min": true,
        "rightSide": false,
        "show": true,
        "sort": "max",
        "sortDesc": true,
        "total": false,
        "values": true
      },
      "lines": true,
      "linewidth": 1,
      "links": [],
      "nullPointMode": "connected",
      "percentage": false,
      "pointradius": 5,
      "points": false,
      "renderer": "flot",
      "seriesOverrides": [
        {
          "alias": "in.*",
          "transform": "negative-Y"
        }
      ],
      "spaceLength": 10,
      "stack": false,
      "steppedLine": false,
      "targets": [
        {
          "expr": "avg(irate(elasticsearch_transport_tx_size_bytes_total{cluster=\"$cluster\",instance=~\"$node\"}[$interval])) by (instance)",
          "format": "time_series",
          "intervalFactor": 2,
          "legendFormat": "Out {{instance}}",
          "refId": "D",
          "step": 10
        },
        {
          "expr": "avg(irate(elasticsearch_transport_rx_size_bytes_total{cluster=\"$cluster\",instance=~\"$node\"}[$interval])) by (instance)",
          "format": "time_series",
          "intervalFactor": 2,
          "legendFormat": "in {{instance}}",
          "refId": "C",
          "step": 10
        }
      ],
      "thresholds": [],
      "timeFrom": null,
      "timeShift": null,
      "title": "Network usage",
      "tooltip": {
        "msResolution": false,
        "shared": true,
        "sort": 0,
        "value_type": "cumulative"
      },
      "transparent": false,
      "type": "graph",
      "xaxis": {
        "buckets": null,
        "mode": "time",
        "name": null,
        "show": true,
        "values": []
      },
      "yaxes": [
        {
          "format": "Bps",
          "label": "Bytes/sec",
          "logBase": 1,
          "max": null,
          "min": null,
          "show": true
        },
        {
          "format": "pps",
          "label": "",
          "logBase": 1,
          "max": null,
          "min": null,
          "show": false
        }
      ],
      "yaxis": {
        "align": false,
        "alignLevel": null
      }
    },
    {
      "collapsed": false,
      "gridPos": {
        "h": 1,
        "w": 24,
        "x": 0,
        "y": 25
      },
      "id": 61,
      "panels": [],
      "repeat": null,
      "title": "Documents",
      "type": "row"
    },
    {
      "aliasColors": {},
      "bars": false,
      "dashLength": 10,
      "dashes": false,
      "datasource": "${DS_PROMETHEUS}",
      "editable": true,
      "error": false,
      "fill": 1,
      "grid": {},
      "gridPos": {
        "h": 10,
        "w": 6,
        "x": 0,
        "y": 26
      },
      "height": "400",
      "id": 1,
      "legend": {
        "alignAsTable": true,
        "avg": true,
        "current": true,
        "hideEmpty": false,
        "hideZero": false,
        "max": true,
        "min": true,
        "rightSide": false,
        "show": true,
        "total": false,
        "values": true
      },
      "lines": true,
      "linewidth": 1,
      "links": [],
      "nullPointMode": "connected",
      "percentage": false,
      "pointradius": 5,
      "points": false,
      "renderer": "flot",
      "seriesOverrides": [],
      "spaceLength": 10,
      "stack": true,
      "steppedLine": false,
      "targets": [
        {
          "expr": "max(elasticsearch_indices_docs) by (instance)",
          "format": "time_series",
          "interval": "",
          "intervalFactor": 2,
          "legendFormat": "{{ instance }}",
          "metric": "",
          "refId": "A",
          "step": 10
        }
      ],
      "thresholds": [],
      "timeFrom": null,
      "timeShift": null,
      "title": "Documents count",
      "tooltip": {
        "msResolution": false,
        "shared": true,
        "sort": 0,
        "value_type": "cumulative"
      },
      "transparent": false,
      "type": "graph",
      "xaxis": {
        "buckets": null,
        "mode": "time",
        "name": null,
        "show": true,
        "values": []
      },
      "yaxes": [
        {
          "format": "short",
          "label": "Documents",
          "logBase": 1,
          "max": null,
          "min": null,
          "show": true
        },
        {
          "format": "short",
          "label": null,
          "logBase": 1,
          "max": null,
          "min": null,
          "show": false
        }
      ],
      "yaxis": {
        "align": false,
        "alignLevel": null
      }
    },
    {
      "aliasColors": {},
      "bars": false,
      "dashLength": 10,
      "dashes": false,
      "datasource": "${DS_PROMETHEUS}",
      "editable": true,
      "error": false,
      "fill": 1,
      "grid": {},
      "gridPos": {
        "h": 10,
        "w": 6,
        "x": 6,
        "y": 26
      },
      "height": "400",
      "id": 24,
      "legend": {
        "alignAsTable": true,
        "avg": true,
        "current": true,
        "hideEmpty": false,
        "hideZero": false,
        "max": true,
        "min": true,
        "rightSide": false,
        "show": true,
        "total": false,
        "values": true
      },
      "lines": true,
      "linewidth": 1,
      "links": [],
      "nullPointMode": "connected",
      "percentage": false,
      "pointradius": 5,
      "points": false,
      "renderer": "flot",
      "seriesOverrides": [],
      "spaceLength": 10,
      "stack": true,
      "steppedLine": false,
      "targets": [
        {
          "expr": "max(irate(elasticsearch_indices_indexing_index_total[$interval])) by (instance)",
          "format": "time_series",
          "interval": "",
          "intervalFactor": 2,
          "legendFormat": "{{ instance }}",
          "metric": "",
          "refId": "A",
          "step": 10
        }
      ],
      "thresholds": [],
      "timeFrom": null,
      "timeShift": null,
      "title": "Documents indexed rate",
      "tooltip": {
        "msResolution": false,
        "shared": true,
        "sort": 0,
        "value_type": "cumulative"
      },
      "transparent": false,
      "type": "graph",
      "xaxis": {
        "buckets": null,
        "mode": "time",
        "name": null,
        "show": true,
        "values": []
      },
      "yaxes": [
        {
          "format": "short",
          "label": "index calls/s",
          "logBase": 1,
          "max": null,
          "min": null,
          "show": true
        },
        {
          "format": "short",
          "label": null,
          "logBase": 1,
          "max": null,
          "min": null,
          "show": false
        }
      ],
      "yaxis": {
        "align": false,
        "alignLevel": null
      }
    },
    {
      "aliasColors": {},
      "bars": false,
      "dashLength": 10,
      "dashes": false,
      "datasource": "${DS_PROMETHEUS}",
      "editable": true,
      "error": false,
      "fill": 1,
      "grid": {},
      "gridPos": {
        "h": 10,
        "w": 6,
        "x": 12,
        "y": 26
      },
      "height": "400",
      "id": 25,
      "legend": {
        "alignAsTable": true,
        "avg": true,
        "current": true,
        "hideEmpty": false,
        "hideZero": false,
        "max": true,
        "min": true,
        "rightSide": false,
        "show": true,
        "total": false,
        "values": true
      },
      "lines": true,
      "linewidth": 1,
      "links": [],
      "nullPointMode": "connected",
      "percentage": false,
      "pointradius": 5,
      "points": false,
      "renderer": "flot",
      "seriesOverrides": [],
      "spaceLength": 10,
      "stack": true,
      "steppedLine": false,
      "targets": [
        {
          "expr": "max (rate(elasticsearch_indices_docs_deleted[$interval]))  by (instance)",
          "format": "time_series",
          "interval": "",
          "intervalFactor": 2,
          "legendFormat": "{{instance}}",
          "metric": "",
          "refId": "A",
          "step": 10
        }
      ],
      "thresholds": [],
      "timeFrom": null,
      "timeShift": null,
      "title": "Documents deleted rate",
      "tooltip": {
        "msResolution": false,
        "shared": true,
        "sort": 0,
        "value_type": "cumulative"
      },
      "transparent": false,
      "type": "graph",
      "xaxis": {
        "buckets": null,
        "mode": "time",
        "name": null,
        "show": true,
        "values": []
      },
      "yaxes": [
        {
          "format": "short",
          "label": "Documents/s",
          "logBase": 1,
          "max": null,
          "min": null,
          "show": true
        },
        {
          "format": "short",
          "label": null,
          "logBase": 1,
          "max": null,
          "min": null,
          "show": false
        }
      ],
      "yaxis": {
        "align": false,
        "alignLevel": null
      }
    },
    {
      "aliasColors": {},
      "bars": false,
      "dashLength": 10,
      "dashes": false,
      "datasource": "${DS_PROMETHEUS}",
      "editable": true,
      "error": false,
      "fill": 1,
      "grid": {},
      "gridPos": {
        "h": 10,
        "w": 6,
        "x": 18,
        "y": 26
      },
      "height": "400",
      "id": 26,
      "legend": {
        "alignAsTable": true,
        "avg": true,
        "current": true,
        "hideEmpty": false,
        "hideZero": false,
        "max": true,
        "min": true,
        "rightSide": false,
        "show": true,
        "total": false,
        "values": true
      },
      "lines": true,
      "linewidth": 1,
      "links": [],
      "nullPointMode": "connected",
      "percentage": false,
      "pointradius": 5,
      "points": false,
      "renderer": "flot",
      "seriesOverrides": [],
      "spaceLength": 10,
      "stack": true,
      "steppedLine": false,
      "targets": [
        {
          "expr": "max( rate(elasticsearch_indices_merges_total{cluster=\"$cluster\",name=~\"$node\"}[$interval])) by (instance)",
          "format": "time_series",
          "interval": "",
          "intervalFactor": 2,
          "legendFormat": "{{instance}}",
          "metric": "",
          "refId": "A",
          "step": 10
        }
      ],
      "thresholds": [],
      "timeFrom": null,
      "timeShift": null,
      "title": "Documents merged rate",
      "tooltip": {
        "msResolution": false,
        "shared": true,
        "sort": 0,
        "value_type": "cumulative"
      },
      "transparent": false,
      "type": "graph",
      "xaxis": {
        "buckets": null,
        "mode": "time",
        "name": null,
        "show": true,
        "values": []
      },
      "yaxes": [
        {
          "format": "short",
          "label": "Documents/s",
          "logBase": 1,
          "max": null,
          "min": null,
          "show": true
        },
        {
          "format": "short",
          "label": null,
          "logBase": 1,
          "max": null,
          "min": null,
          "show": false
        }
      ],
      "yaxis": {
        "align": false,
        "alignLevel": null
      }
    },
    {
      "collapsed": false,
      "gridPos": {
        "h": 1,
        "w": 24,
        "x": 0,
        "y": 36
      },
      "id": 62,
      "panels": [],
      "repeat": null,
      "title": "Total Operations stats",
      "type": "row"
    },
    {
      "aliasColors": {},
      "bars": false,
      "dashLength": 10,
      "dashes": false,
      "datasource": "${DS_PROMETHEUS}",
      "editable": true,
      "error": false,
      "fill": 1,
      "grid": {},
      "gridPos": {
        "h": 10,
        "w": 12,
        "x": 0,
        "y": 37
      },
      "height": "400",
      "id": 48,
      "legend": {
        "alignAsTable": true,
        "avg": true,
        "current": true,
        "hideEmpty": false,
        "hideZero": false,
        "max": true,
        "min": true,
        "rightSide": false,
        "show": true,
        "sort": "avg",
        "sortDesc": true,
        "total": false,
        "values": true
      },
      "lines": true,
      "linewidth": 1,
      "links": [],
      "nullPointMode": "connected",
      "percentage": false,
      "pointradius": 5,
      "points": false,
      "renderer": "flot",
      "seriesOverrides": [],
      "spaceLength": 10,
      "stack": false,
      "steppedLine": false,
      "targets": [
        {
          "expr": "sum(max(irate(elasticsearch_indices_indexing_index_total[$interval]))  by (instance))",
          "format": "time_series",
          "interval": "",
          "intervalFactor": 2,
          "legendFormat": "indexing",
          "metric": "",
          "refId": "A",
          "step": 4
        },
        {
          "expr": "sum(max(irate(elasticsearch_indices_search_query_total[$interval])) by (instance))",
          "format": "time_series",
          "intervalFactor": 2,
          "legendFormat": "query",
          "refId": "B",
          "step": 4
        },
        {
          "expr": "sum(max( irate(elasticsearch_indices_search_fetch_total[$interval])) by (instance))",
          "format": "time_series",
          "intervalFactor": 2,
          "legendFormat": "fetch",
          "refId": "C",
          "step": 4
        },
        {
          "expr": "sum(max (irate(elasticsearch_indices_merges_total[$interval]))  by (instance))",
          "format": "time_series",
          "intervalFactor": 2,
          "legendFormat": "merges",
          "refId": "D",
          "step": 4
        },
        {
          "expr": "irate(elasticsearch_indices_refresh_total{cluster=\"$cluster\",name=~\"$node\"}[$interval])",
          "format": "time_series",
          "intervalFactor": 2,
          "legendFormat": "{{ name }} - refresh",
          "refId": "E",
          "step": 4
        },
        {
          "expr": "sum(max(irate(elasticsearch_indices_flush_total[$interval])) by (instance))",
          "format": "time_series",
          "intervalFactor": 2,
          "legendFormat": "flush",
          "refId": "F",
          "step": 4
        }
      ],
      "thresholds": [],
      "timeFrom": null,
      "timeShift": null,
      "title": "Total Operations  rate",
      "tooltip": {
        "msResolution": false,
        "shared": true,
        "sort": 2,
        "value_type": "cumulative"
      },
      "transparent": false,
      "type": "graph",
      "xaxis": {
        "buckets": null,
        "mode": "time",
        "name": null,
        "show": true,
        "values": []
      },
      "yaxes": [
        {
          "format": "short",
          "label": "Operations/s",
          "logBase": 1,
          "max": null,
          "min": null,
          "show": true
        },
        {
          "format": "short",
          "label": null,
          "logBase": 1,
          "max": null,
          "min": null,
          "show": false
        }
      ],
      "yaxis": {
        "align": false,
        "alignLevel": null
      }
    },
    {
      "aliasColors": {},
      "bars": false,
      "dashLength": 10,
      "dashes": false,
      "datasource": "${DS_PROMETHEUS}",
      "editable": true,
      "error": false,
      "fill": 1,
      "grid": {},
      "gridPos": {
        "h": 10,
        "w": 12,
        "x": 12,
        "y": 37
      },
      "height": "400",
      "id": 49,
      "legend": {
        "alignAsTable": true,
        "avg": true,
        "current": true,
        "hideEmpty": false,
        "hideZero": false,
        "max": true,
        "min": true,
        "rightSide": false,
        "show": true,
        "sort": "avg",
        "sortDesc": true,
        "total": false,
        "values": true
      },
      "lines": true,
      "linewidth": 1,
      "links": [],
      "nullPointMode": "connected",
      "percentage": false,
      "pointradius": 5,
      "points": false,
      "renderer": "flot",
      "seriesOverrides": [],
      "spaceLength": 10,
      "stack": false,
      "steppedLine": false,
      "targets": [
        {
          "expr": "max(irate(elasticsearch_indices_indexing_index_time_seconds_total[$interval])) by (instance)",
          "format": "time_series",
          "hide": false,
          "interval": "",
          "intervalFactor": 2,
          "legendFormat": "{{ instance }} index time",
          "metric": "",
          "refId": "A",
          "step": 4
        },
        {
          "expr": "max(irate(elasticsearch_indices_search_query_time_ms_total[$interval])) by (instance)",
          "format": "time_series",
          "intervalFactor": 2,
          "legendFormat": "{{ instance }} - query",
          "refId": "B",
          "step": 4
        },
        {
          "expr": "max(irate(elasticsearch_indices_search_fetch_time_ms_total[$interval])) by (instance)",
          "format": "time_series",
          "intervalFactor": 2,
          "legendFormat": "{{ instance }} - fetch",
          "refId": "C",
          "step": 4
        },
        {
          "expr": "max(irate(elasticsearch_indices_merges_total_time_ms_total[$interval])) by (instance)",
          "format": "time_series",
          "intervalFactor": 2,
          "legendFormat": "{{ instance }} - merges",
          "refId": "D",
          "step": 4
        },
        {
          "expr": "max(irate(elasticsearch_indices_refresh_total_time_ms_total[$interval])) by (instance)",
          "format": "time_series",
          "intervalFactor": 2,
          "legendFormat": "{{ instance }} - refresh",
          "refId": "E",
          "step": 4
        },
        {
          "expr": "max(irate(elasticsearch_indices_flush_time_ms_total[$interval])) by (instance)",
          "format": "time_series",
          "intervalFactor": 2,
          "legendFormat": "{{ instance }} - flush",
          "refId": "F",
          "step": 4
        }
      ],
      "thresholds": [],
      "timeFrom": null,
      "timeShift": null,
      "title": "Total Operations  time",
      "tooltip": {
        "msResolution": false,
        "shared": true,
        "sort": 2,
        "value_type": "cumulative"
      },
      "transparent": false,
      "type": "graph",
      "xaxis": {
        "buckets": null,
        "mode": "time",
        "name": null,
        "show": true,
        "values": []
      },
      "yaxes": [
        {
          "format": "ms",
          "label": "Time",
          "logBase": 1,
          "max": null,
          "min": null,
          "show": true
        },
        {
          "format": "short",
          "label": null,
          "logBase": 1,
          "max": null,
          "min": null,
          "show": false
        }
      ],
      "yaxis": {
        "align": false,
        "alignLevel": null
      }
    },
    {
      "collapsed": false,
      "gridPos": {
        "h": 1,
        "w": 24,
        "x": 0,
        "y": 47
      },
      "id": 63,
      "panels": [],
      "repeat": null,
      "title": "Times",
      "type": "row"
    },
    {
      "aliasColors": {},
      "bars": false,
      "dashLength": 10,
      "dashes": false,
      "datasource": "${DS_PROMETHEUS}",
      "editable": true,
      "error": false,
      "fill": 1,
      "grid": {},
      "gridPos": {
        "h": 10,
        "w": 8,
        "x": 0,
        "y": 48
      },
      "height": "400",
      "id": 33,
      "legend": {
        "alignAsTable": true,
        "avg": true,
        "current": true,
        "hideEmpty": false,
        "hideZero": false,
        "max": true,
        "min": true,
        "rightSide": false,
        "show": true,
        "total": false,
        "values": true
      },
      "lines": true,
      "linewidth": 1,
      "links": [],
      "nullPointMode": "connected",
      "percentage": false,
      "pointradius": 5,
      "points": false,
      "renderer": "flot",
      "seriesOverrides": [],
      "spaceLength": 10,
      "stack": false,
      "steppedLine": false,
      "targets": [
        {
          "expr": "max(rate(elasticsearch_indices_search_query_time_seconds[$interval])) by (instance)",
          "format": "time_series",
          "interval": "",
          "intervalFactor": 2,
          "legendFormat": "{{ instance }}",
          "metric": "",
          "refId": "A",
          "step": 4
        }
      ],
      "thresholds": [],
      "timeFrom": null,
      "timeShift": null,
      "title": "Query time",
      "tooltip": {
        "msResolution": false,
        "shared": true,
        "sort": 0,
        "value_type": "cumulative"
      },
      "transparent": false,
      "type": "graph",
      "xaxis": {
        "buckets": null,
        "mode": "time",
        "name": null,
        "show": true,
        "values": []
      },
      "yaxes": [
        {
          "format": "ms",
          "label": "Time",
          "logBase": 1,
          "max": null,
          "min": null,
          "show": true
        },
        {
          "format": "short",
          "label": null,
          "logBase": 1,
          "max": null,
          "min": null,
          "show": false
        }
      ],
      "yaxis": {
        "align": false,
        "alignLevel": null
      }
    },
    {
      "aliasColors": {},
      "bars": false,
      "dashLength": 10,
      "dashes": false,
      "datasource": "${DS_PROMETHEUS}",
      "editable": true,
      "error": false,
      "fill": 1,
      "grid": {},
      "gridPos": {
        "h": 10,
        "w": 8,
        "x": 8,
        "y": 48
      },
      "height": "400",
      "id": 5,
      "legend": {
        "alignAsTable": true,
        "avg": true,
        "current": true,
        "hideEmpty": false,
        "hideZero": false,
        "max": true,
        "min": true,
        "rightSide": false,
        "show": true,
        "total": false,
        "values": true
      },
      "lines": true,
      "linewidth": 1,
      "links": [],
      "nullPointMode": "connected",
      "percentage": false,
      "pointradius": 5,
      "points": false,
      "renderer": "flot",
      "seriesOverrides": [],
      "spaceLength": 10,
      "stack": false,
      "steppedLine": false,
      "targets": [
        {
          "expr": "max(rate(elasticsearch_indices_indexing_index_time_seconds_total[$interval])) by (instance)",
          "format": "time_series",
          "interval": "",
          "intervalFactor": 2,
          "legendFormat": "{{instance}}",
          "metric": "",
          "refId": "A",
          "step": 4
        }
      ],
      "thresholds": [],
      "timeFrom": null,
      "timeShift": null,
      "title": "Indexing time",
      "tooltip": {
        "msResolution": false,
        "shared": true,
        "sort": 0,
        "value_type": "cumulative"
      },
      "transparent": false,
      "type": "graph",
      "xaxis": {
        "buckets": null,
        "mode": "time",
        "name": null,
        "show": true,
        "values": []
      },
      "yaxes": [
        {
          "format": "ms",
          "label": "Time",
          "logBase": 1,
          "max": null,
          "min": null,
          "show": true
        },
        {
          "format": "short",
          "label": null,
          "logBase": 1,
          "max": null,
          "min": null,
          "show": false
        }
      ],
      "yaxis": {
        "align": false,
        "alignLevel": null
      }
    },
    {
      "aliasColors": {},
      "bars": false,
      "dashLength": 10,
      "dashes": false,
      "datasource": "${DS_PROMETHEUS}",
      "editable": true,
      "error": false,
      "fill": 1,
      "grid": {},
      "gridPos": {
        "h": 10,
        "w": 8,
        "x": 16,
        "y": 48
      },
      "height": "400",
      "id": 3,
      "legend": {
        "alignAsTable": true,
        "avg": true,
        "current": true,
        "hideEmpty": false,
        "hideZero": false,
        "max": true,
        "min": true,
        "rightSide": false,
        "show": true,
        "total": false,
        "values": true
      },
      "lines": true,
      "linewidth": 1,
      "links": [],
      "nullPointMode": "connected",
      "percentage": false,
      "pointradius": 5,
      "points": false,
      "renderer": "flot",
      "seriesOverrides": [],
      "spaceLength": 10,
      "stack": false,
      "steppedLine": false,
      "targets": [
        {
          "expr": "max(rate(elasticsearch_indices_merges_total_time_seconds_total[$interval])) by (instance)",
          "format": "time_series",
          "interval": "",
          "intervalFactor": 2,
          "legendFormat": "{{instance}}",
          "metric": "",
          "refId": "A",
          "step": 4
        }
      ],
      "thresholds": [],
      "timeFrom": null,
      "timeShift": null,
      "title": "Merging time",
      "tooltip": {
        "msResolution": false,
        "shared": true,
        "sort": 0,
        "value_type": "cumulative"
      },
      "transparent": false,
      "type": "graph",
      "xaxis": {
        "buckets": null,
        "mode": "time",
        "name": null,
        "show": true,
        "values": []
      },
      "yaxes": [
        {
          "format": "s",
          "label": "Time",
          "logBase": 1,
          "max": null,
          "min": null,
          "show": true
        },
        {
          "format": "short",
          "label": null,
          "logBase": 1,
          "max": null,
          "min": null,
          "show": false
        }
      ],
      "yaxis": {
        "align": false,
        "alignLevel": null
      }
    },
    {
      "collapsed": false,
      "gridPos": {
        "h": 1,
        "w": 24,
        "x": 0,
        "y": 58
      },
      "id": 64,
      "panels": [],
      "repeat": null,
      "title": "Caches",
      "type": "row"
    },
    {
      "aliasColors": {},
      "bars": false,
      "dashLength": 10,
      "dashes": false,
      "datasource": "${DS_PROMETHEUS}",
      "editable": true,
      "error": false,
      "fill": 1,
      "grid": {},
      "gridPos": {
        "h": 10,
        "w": 6,
        "x": 0,
        "y": 59
      },
      "height": "400",
      "id": 4,
      "legend": {
        "alignAsTable": true,
        "avg": true,
        "current": true,
        "hideEmpty": false,
        "hideZero": false,
        "max": true,
        "min": true,
        "rightSide": false,
        "show": true,
        "total": false,
        "values": true
      },
      "lines": true,
      "linewidth": 1,
      "links": [],
      "nullPointMode": "connected",
      "percentage": false,
      "pointradius": 5,
      "points": false,
      "renderer": "flot",
      "seriesOverrides": [],
      "spaceLength": 10,
      "stack": true,
      "steppedLine": false,
      "targets": [
        {
          "expr": "max(elasticsearch_indices_fielddata_memory_size_bytes) by (instance)",
          "format": "time_series",
          "interval": "",
          "intervalFactor": 2,
          "legendFormat": "{{instance}}",
          "metric": "",
          "refId": "A",
          "step": 10
        }
      ],
      "thresholds": [],
      "timeFrom": null,
      "timeShift": null,
      "title": "Field data memory size",
      "tooltip": {
        "msResolution": false,
        "shared": true,
        "sort": 0,
        "value_type": "cumulative"
      },
      "transparent": false,
      "type": "graph",
      "xaxis": {
        "buckets": null,
        "mode": "time",
        "name": null,
        "show": true,
        "values": []
      },
      "yaxes": [
        {
          "format": "bytes",
          "label": "Memory",
          "logBase": 1,
          "max": null,
          "min": null,
          "show": true
        },
        {
          "format": "short",
          "label": null,
          "logBase": 1,
          "max": null,
          "min": null,
          "show": false
        }
      ],
      "yaxis": {
        "align": false,
        "alignLevel": null
      }
    },
    {
      "aliasColors": {},
      "bars": false,
      "dashLength": 10,
      "dashes": false,
      "datasource": "${DS_PROMETHEUS}",
      "editable": true,
      "error": false,
      "fill": 1,
      "grid": {},
      "gridPos": {
        "h": 10,
        "w": 6,
        "x": 6,
        "y": 59
      },
      "height": "400",
      "id": 34,
      "legend": {
        "alignAsTable": true,
        "avg": true,
        "current": true,
        "hideEmpty": false,
        "hideZero": false,
        "max": true,
        "min": true,
        "rightSide": false,
        "show": true,
        "total": false,
        "values": true
      },
      "lines": true,
      "linewidth": 1,
      "links": [],
      "nullPointMode": "connected",
      "percentage": false,
      "pointradius": 5,
      "points": false,
      "renderer": "flot",
      "seriesOverrides": [],
      "spaceLength": 10,
      "stack": true,
      "steppedLine": false,
      "targets": [
        {
          "expr": "max (rate(elasticsearch_indices_fielddata_evictions[$interval])) by (instance)",
          "format": "time_series",
          "interval": "",
          "intervalFactor": 2,
          "legendFormat": "{{instance}}",
          "metric": "",
          "refId": "A",
          "step": 10
        }
      ],
      "thresholds": [],
      "timeFrom": null,
      "timeShift": null,
      "title": "Field data evictions",
      "tooltip": {
        "msResolution": false,
        "shared": true,
        "sort": 0,
        "value_type": "cumulative"
      },
      "transparent": false,
      "type": "graph",
      "xaxis": {
        "buckets": null,
        "mode": "time",
        "name": null,
        "show": true,
        "values": []
      },
      "yaxes": [
        {
          "format": "short",
          "label": "Evictions/s",
          "logBase": 1,
          "max": null,
          "min": null,
          "show": true
        },
        {
          "format": "short",
          "label": null,
          "logBase": 1,
          "max": null,
          "min": null,
          "show": false
        }
      ],
      "yaxis": {
        "align": false,
        "alignLevel": null
      }
    },
    {
      "aliasColors": {},
      "bars": false,
      "dashLength": 10,
      "dashes": false,
      "datasource": "${DS_PROMETHEUS}",
      "editable": true,
      "error": false,
      "fill": 1,
      "grid": {},
      "gridPos": {
        "h": 10,
        "w": 6,
        "x": 12,
        "y": 59
      },
      "height": "400",
      "id": 35,
      "legend": {
        "alignAsTable": true,
        "avg": true,
        "current": true,
        "hideEmpty": false,
        "hideZero": false,
        "max": true,
        "min": true,
        "rightSide": false,
        "show": true,
        "total": false,
        "values": true
      },
      "lines": true,
      "linewidth": 1,
      "links": [],
      "nullPointMode": "connected",
      "percentage": false,
      "pointradius": 5,
      "points": false,
      "renderer": "flot",
      "seriesOverrides": [],
      "spaceLength": 10,
      "stack": true,
      "steppedLine": false,
      "targets": [
        {
          "expr": "max(elasticsearch_indices_query_cache_memory_size_bytes) by (instance)",
          "format": "time_series",
          "interval": "",
          "intervalFactor": 2,
          "legendFormat": "{{instance}}",
          "metric": "",
          "refId": "A",
          "step": 10
        }
      ],
      "thresholds": [],
      "timeFrom": null,
      "timeShift": null,
      "title": "Query cache size",
      "tooltip": {
        "msResolution": false,
        "shared": true,
        "sort": 0,
        "value_type": "cumulative"
      },
      "transparent": false,
      "type": "graph",
      "xaxis": {
        "buckets": null,
        "mode": "time",
        "name": null,
        "show": true,
        "values": []
      },
      "yaxes": [
        {
          "format": "bytes",
          "label": "Size",
          "logBase": 1,
          "max": null,
          "min": null,
          "show": true
        },
        {
          "format": "short",
          "label": null,
          "logBase": 1,
          "max": null,
          "min": null,
          "show": false
        }
      ],
      "yaxis": {
        "align": false,
        "alignLevel": null
      }
    },
    {
      "aliasColors": {},
      "bars": false,
      "dashLength": 10,
      "dashes": false,
      "datasource": "${DS_PROMETHEUS}",
      "editable": true,
      "error": false,
      "fill": 1,
      "grid": {},
      "gridPos": {
        "h": 10,
        "w": 6,
        "x": 18,
        "y": 59
      },
      "height": "400",
      "id": 36,
      "legend": {
        "alignAsTable": true,
        "avg": true,
        "current": true,
        "hideEmpty": false,
        "hideZero": false,
        "max": true,
        "min": true,
        "rightSide": false,
        "show": true,
        "total": false,
        "values": true
      },
      "lines": true,
      "linewidth": 1,
      "links": [],
      "nullPointMode": "connected",
      "percentage": false,
      "pointradius": 5,
      "points": false,
      "renderer": "flot",
      "seriesOverrides": [],
      "spaceLength": 10,
      "stack": true,
      "steppedLine": false,
      "targets": [
        {
          "expr": "max(rate(elasticsearch_indices_query_cache_evictions[$interval])) by (instance)",
          "format": "time_series",
          "interval": "",
          "intervalFactor": 2,
          "legendFormat": "{{instance}}",
          "metric": "",
          "refId": "A",
          "step": 10
        }
      ],
      "thresholds": [],
      "timeFrom": null,
      "timeShift": null,
      "title": "Query cache evictions",
      "tooltip": {
        "msResolution": false,
        "shared": true,
        "sort": 0,
        "value_type": "cumulative"
      },
      "transparent": false,
      "type": "graph",
      "xaxis": {
        "buckets": null,
        "mode": "time",
        "name": null,
        "show": true,
        "values": []
      },
      "yaxes": [
        {
          "format": "short",
          "label": "Evictions/s",
          "logBase": 1,
          "max": null,
          "min": null,
          "show": true
        },
        {
          "format": "short",
          "label": null,
          "logBase": 1,
          "max": null,
          "min": null,
          "show": false
        }
      ],
      "yaxis": {
        "align": false,
        "alignLevel": null
      }
    },
    {
      "collapsed": false,
      "gridPos": {
        "h": 1,
        "w": 24,
        "x": 0,
        "y": 69
      },
      "id": 65,
      "panels": [],
      "repeat": null,
      "title": "Thread Pool",
      "type": "row"
    },
    {
      "aliasColors": {},
      "bars": false,
      "dashLength": 10,
      "dashes": false,
      "datasource": "${DS_PROMETHEUS}",
      "editable": true,
      "error": false,
      "fill": 1,
      "gridPos": {
        "h": 13,
        "w": 6,
        "x": 0,
        "y": 70
      },
      "id": 45,
      "legend": {
        "alignAsTable": true,
        "avg": true,
        "current": false,
        "max": true,
        "min": true,
        "show": true,
        "sort": "avg",
        "sortDesc": true,
        "total": false,
        "values": true
      },
      "lines": true,
      "linewidth": 1,
      "links": [],
      "nullPointMode": "connected",
      "percentage": false,
      "pointradius": 5,
      "points": false,
      "renderer": "flot",
      "seriesOverrides": [],
      "spaceLength": 10,
      "stack": false,
      "steppedLine": false,
      "targets": [
        {
          "expr": " max(irate(elasticsearch_thread_pool_rejected_count[$interval])) by (instance)",
          "format": "time_series",
          "intervalFactor": 2,
          "legendFormat": "{{instance}}",
          "refId": "A",
          "step": 10
        }
      ],
      "thresholds": [],
      "timeFrom": null,
      "timeShift": null,
      "title": "Thread Pool operations rejected",
      "tooltip": {
        "msResolution": false,
        "shared": true,
        "sort": 2,
        "value_type": "individual"
      },
      "type": "graph",
      "xaxis": {
        "buckets": null,
        "mode": "time",
        "name": null,
        "show": true,
        "values": []
      },
      "yaxes": [
        {
          "format": "short",
          "label": null,
          "logBase": 1,
          "max": null,
          "min": null,
          "show": true
        },
        {
          "format": "short",
          "label": null,
          "logBase": 1,
          "max": null,
          "min": null,
          "show": true
        }
      ],
      "yaxis": {
        "align": false,
        "alignLevel": null
      }
    },
    {
      "aliasColors": {},
      "bars": false,
      "dashLength": 10,
      "dashes": false,
      "datasource": "${DS_PROMETHEUS}",
      "editable": true,
      "error": false,
      "fill": 1,
      "gridPos": {
        "h": 13,
        "w": 6,
        "x": 6,
        "y": 70
      },
      "id": 46,
      "legend": {
        "alignAsTable": true,
        "avg": true,
        "current": false,
        "max": true,
        "min": true,
        "show": true,
        "sort": "avg",
        "sortDesc": true,
        "total": false,
        "values": true
      },
      "lines": true,
      "linewidth": 1,
      "links": [],
      "nullPointMode": "connected",
      "percentage": false,
      "pointradius": 5,
      "points": false,
      "renderer": "flot",
      "seriesOverrides": [],
      "spaceLength": 10,
      "stack": false,
      "steppedLine": false,
      "targets": [
        {
          "expr": "max(elasticsearch_thread_pool_active_count) by (instance)",
          "format": "time_series",
          "intervalFactor": 2,
          "legendFormat": "{{ instance }}",
          "refId": "A",
          "step": 10
        }
      ],
      "thresholds": [],
      "timeFrom": null,
      "timeShift": null,
      "title": "Thread Pool operations queued",
      "tooltip": {
        "msResolution": false,
        "shared": true,
        "sort": 2,
        "value_type": "individual"
      },
      "type": "graph",
      "xaxis": {
        "buckets": null,
        "mode": "time",
        "name": null,
        "show": true,
        "values": []
      },
      "yaxes": [
        {
          "format": "short",
          "label": null,
          "logBase": 1,
          "max": null,
          "min": null,
          "show": true
        },
        {
          "format": "short",
          "label": null,
          "logBase": 1,
          "max": null,
          "min": null,
          "show": true
        }
      ],
      "yaxis": {
        "align": false,
        "alignLevel": null
      }
    },
    {
      "aliasColors": {},
      "bars": false,
      "dashLength": 10,
      "dashes": false,
      "datasource": "${DS_PROMETHEUS}",
      "editable": true,
      "error": false,
      "fill": 1,
      "gridPos": {
        "h": 13,
        "w": 6,
        "x": 12,
        "y": 70
      },
      "height": "",
      "id": 43,
      "legend": {
        "alignAsTable": true,
        "avg": true,
        "current": false,
        "max": true,
        "min": true,
        "show": true,
        "sort": "avg",
        "sortDesc": true,
        "total": false,
        "values": true
      },
      "lines": true,
      "linewidth": 1,
      "links": [],
      "nullPointMode": "connected",
      "percentage": false,
      "pointradius": 5,
      "points": false,
      "renderer": "flot",
      "seriesOverrides": [],
      "spaceLength": 10,
      "stack": false,
      "steppedLine": false,
      "targets": [
        {
          "expr": "max(elasticsearch_thread_pool_active_count) by (instance)",
          "format": "time_series",
          "intervalFactor": 2,
          "legendFormat": "{{instance}}",
          "refId": "A",
          "step": 10
        }
      ],
      "thresholds": [],
      "timeFrom": null,
      "timeShift": null,
      "title": "Thread Pool threads active",
      "tooltip": {
        "msResolution": false,
        "shared": true,
        "sort": 2,
        "value_type": "individual"
      },
      "type": "graph",
      "xaxis": {
        "buckets": null,
        "mode": "time",
        "name": null,
        "show": true,
        "values": []
      },
      "yaxes": [
        {
          "format": "short",
          "label": null,
          "logBase": 1,
          "max": null,
          "min": null,
          "show": true
        },
        {
          "format": "short",
          "label": null,
          "logBase": 1,
          "max": null,
          "min": null,
          "show": true
        }
      ],
      "yaxis": {
        "align": false,
        "alignLevel": null
      }
    },
    {
      "aliasColors": {},
      "bars": false,
      "dashLength": 10,
      "dashes": false,
      "datasource": "${DS_PROMETHEUS}",
      "editable": true,
      "error": false,
      "fill": 1,
      "gridPos": {
        "h": 13,
        "w": 6,
        "x": 18,
        "y": 70
      },
      "id": 44,
      "legend": {
        "alignAsTable": true,
        "avg": true,
        "current": false,
        "max": true,
        "min": true,
        "show": true,
        "sort": "avg",
        "sortDesc": true,
        "total": false,
        "values": true
      },
      "lines": true,
      "linewidth": 1,
      "links": [],
      "nullPointMode": "connected",
      "percentage": false,
      "pointradius": 5,
      "points": false,
      "renderer": "flot",
      "seriesOverrides": [],
      "spaceLength": 10,
      "stack": false,
      "steppedLine": false,
      "targets": [
        {
          "expr": "max(irate(elasticsearch_thread_pool_completed_count[$interval])) by (instance)",
          "format": "time_series",
          "intervalFactor": 2,
          "legendFormat": "{{instance}}",
          "refId": "A",
          "step": 10
        }
      ],
      "thresholds": [],
      "timeFrom": null,
      "timeShift": null,
      "title": "Thread Pool operations completed",
      "tooltip": {
        "msResolution": false,
        "shared": true,
        "sort": 2,
        "value_type": "individual"
      },
      "type": "graph",
      "xaxis": {
        "buckets": null,
        "mode": "time",
        "name": null,
        "show": true,
        "values": []
      },
      "yaxes": [
        {
          "format": "short",
          "label": null,
          "logBase": 1,
          "max": null,
          "min": null,
          "show": true
        },
        {
          "format": "short",
          "label": null,
          "logBase": 1,
          "max": null,
          "min": null,
          "show": true
        }
      ],
      "yaxis": {
        "align": false,
        "alignLevel": null
      }
    },
    {
      "collapsed": false,
      "gridPos": {
        "h": 1,
        "w": 24,
        "x": 0,
        "y": 83
      },
      "id": 66,
      "panels": [],
      "repeat": null,
      "title": "JVM Garbage Collection",
      "type": "row"
    },
    {
      "aliasColors": {},
      "bars": false,
      "dashLength": 10,
      "dashes": false,
      "datasource": "${DS_PROMETHEUS}",
      "editable": true,
      "error": false,
      "fill": 1,
      "grid": {},
      "gridPos": {
        "h": 10,
        "w": 12,
        "x": 0,
        "y": 84
      },
      "height": "400",
      "id": 7,
      "legend": {
        "alignAsTable": true,
        "avg": true,
        "current": true,
        "hideEmpty": false,
        "hideZero": false,
        "max": true,
        "min": true,
        "rightSide": false,
        "show": true,
        "total": false,
        "values": true
      },
      "lines": true,
      "linewidth": 1,
      "links": [],
      "nullPointMode": "connected",
      "percentage": false,
      "pointradius": 5,
      "points": false,
      "renderer": "flot",
      "seriesOverrides": [],
      "spaceLength": 10,
      "stack": true,
      "steppedLine": false,
      "targets": [
        {
          "expr": "max(rate(elasticsearch_jvm_gc_collection_seconds_count[$interval])) by (instance)",
          "format": "time_series",
          "interval": "",
          "intervalFactor": 2,
          "legendFormat": "{{instance}} ",
          "metric": "",
          "refId": "A",
          "step": 4
        }
      ],
      "thresholds": [],
      "timeFrom": null,
      "timeShift": null,
      "title": "GC count",
      "tooltip": {
        "msResolution": false,
        "shared": true,
        "sort": 0,
        "value_type": "cumulative"
      },
      "transparent": false,
      "type": "graph",
      "xaxis": {
        "buckets": null,
        "mode": "time",
        "name": null,
        "show": true,
        "values": []
      },
      "yaxes": [
        {
          "format": "short",
          "label": "GCs",
          "logBase": 1,
          "max": null,
          "min": null,
          "show": true
        },
        {
          "format": "short",
          "label": null,
          "logBase": 1,
          "max": null,
          "min": null,
          "show": false
        }
      ],
      "yaxis": {
        "align": false,
        "alignLevel": null
      }
    },
    {
      "aliasColors": {},
      "bars": false,
      "dashLength": 10,
      "dashes": false,
      "datasource": "${DS_PROMETHEUS}",
      "editable": true,
      "error": false,
      "fill": 1,
      "grid": {},
      "gridPos": {
        "h": 10,
        "w": 12,
        "x": 12,
        "y": 84
      },
      "height": "400",
      "id": 27,
      "legend": {
        "alignAsTable": true,
        "avg": true,
        "current": true,
        "hideEmpty": false,
        "hideZero": false,
        "max": true,
        "min": true,
        "rightSide": false,
        "show": true,
        "total": false,
        "values": true
      },
      "lines": true,
      "linewidth": 1,
      "links": [],
      "nullPointMode": "connected",
      "percentage": false,
      "pointradius": 5,
      "points": false,
      "renderer": "flot",
      "seriesOverrides": [],
      "spaceLength": 10,
      "stack": false,
      "steppedLine": false,
      "targets": [
        {
          "expr": "max(rate(elasticsearch_jvm_gc_collection_seconds_count[$interval])) by (instance)",
          "format": "time_series",
          "interval": "",
          "intervalFactor": 2,
          "legendFormat": "{{instance}} - {{gc}}",
          "metric": "",
          "refId": "A",
          "step": 4
        }
      ],
      "thresholds": [],
      "timeFrom": null,
      "timeShift": null,
      "title": "GC time",
      "tooltip": {
        "msResolution": false,
        "shared": true,
        "sort": 0,
        "value_type": "cumulative"
      },
      "transparent": false,
      "type": "graph",
      "xaxis": {
        "buckets": null,
        "mode": "time",
        "name": null,
        "show": true,
        "values": []
      },
      "yaxes": [
        {
          "format": "s",
          "label": "Time",
          "logBase": 1,
          "max": null,
          "min": null,
          "show": true
        },
        {
          "format": "short",
          "label": null,
          "logBase": 1,
          "max": null,
          "min": null,
          "show": false
        }
      ],
      "yaxis": {
        "align": false,
        "alignLevel": null
      }
    }
  ],
  "refresh": "30s",
  "schemaVersion": 16,
  "style": "dark",
  "tags": [
    "elasticsearch",
    "App"
  ],
  "templating": {
    "list": [
      {
        "auto": true,
        "auto_count": 30,
        "auto_min": "10s",
        "current": {
          "text": "auto",
          "value": "$__auto_interval_interval"
        },
        "hide": 0,
        "label": "Interval",
        "name": "interval",
        "options": [
          {
            "selected": true,
            "text": "auto",
            "value": "$__auto_interval_interval"
          },
          {
            "selected": false,
            "text": "1m",
            "value": "1m"
          },
          {
            "selected": false,
            "text": "10m",
            "value": "10m"
          },
          {
            "selected": false,
            "text": "30m",
            "value": "30m"
          },
          {
            "selected": false,
            "text": "1h",
            "value": "1h"
          },
          {
            "selected": false,
            "text": "6h",
            "value": "6h"
          },
          {
            "selected": false,
            "text": "12h",
            "value": "12h"
          },
          {
            "selected": false,
            "text": "1d",
            "value": "1d"
          },
          {
            "selected": false,
            "text": "7d",
            "value": "7d"
          },
          {
            "selected": false,
            "text": "14d",
            "value": "14d"
          },
          {
            "selected": false,
            "text": "30d",
            "value": "30d"
          }
        ],
        "query": "1m,10m,30m,1h,6h,12h,1d,7d,14d,30d",
        "refresh": 2,
        "skipUrlSync": false,
        "type": "interval"
      },
      {
        "allValue": null,
        "current": {},
        "datasource": "${DS_PROMETHEUS}",
        "hide": 0,
        "includeAll": false,
        "label": "cluster",
        "multi": false,
        "name": "cluster",
        "options": [],
        "query": "label_values(elasticsearch_cluster_health_status,cluster)",
        "refresh": 1,
        "regex": "",
        "skipUrlSync": false,
        "sort": 1,
        "tagValuesQuery": null,
        "tags": [],
        "tagsQuery": null,
        "type": "query",
        "useTags": false
      },
      {
        "allValue": null,
        "current": {},
        "datasource": "${DS_PROMETHEUS}",
        "hide": 0,
        "includeAll": true,
        "label": "node",
        "multi": true,
        "name": "node",
        "options": [],
        "query": "label_values(elasticsearch_cluster_health_up,instance)",
        "refresh": 1,
        "regex": "",
        "skipUrlSync": false,
        "sort": 1,
        "tagValuesQuery": null,
        "tags": [],
        "tagsQuery": null,
        "type": "query",
        "useTags": false
      },
      {
        "allValue": null,
        "current": {},
        "datasource": "${DS_PROMETHEUS}",
        "hide": 0,
        "includeAll": false,
        "label": "Instance",
        "multi": false,
        "name": "copy_of_cluster",
        "options": [],
        "query": "label_values(elasticsearch_cluster_health_status,cluster)",
        "refresh": 1,
        "regex": "",
        "skipUrlSync": false,
        "sort": 1,
        "tagValuesQuery": null,
        "tags": [],
        "tagsQuery": null,
        "type": "query",
        "useTags": false
      }
    ]
  },
  "time": {
    "from": "now-24h",
    "to": "now"
  },
  "timepicker": {
    "refresh_intervals": [
      "5s",
      "10s",
      "30s",
      "1m",
      "5m",
      "15m",
      "30m",
      "1h",
      "2h",
      "1d"
    ],
    "time_options": [
      "5m",
      "15m",
      "1h",
      "6h",
      "12h",
      "24h",
      "2d",
      "7d",
      "30d"
    ]
  },
  "timezone": "browser",
  "title": "Elasticsearch",
  "uid": "000000004",
  "version": 2
}